Spruce_iri-0.2.0-py2.7-nspkg.pth
spruce/iri/goose.py
spruce/iri/__init__.py
spruce/iri/_codecs.py
Spruce_iri-0.2.0.dist-info/METADATA
Spruce_iri-0.2.0.dist-info/entry_points.txt
Spruce_iri-0.2.0.dist-info/RECORD
Spruce_iri-0.2.0.dist-info/top_level.txt
Spruce_iri-0.2.0.dist-info/namespace_packages.txt
Spruce_iri-0.2.0.dist-info/WHEEL
Spruce_iri-0.2.0.dist-info/metadata.json
Spruce_iri-0.2.0.dist-info/DESCRIPTION.rst
