Metadata-Version: 2.0
Name: Spruce-iri
Version: 0.2.0
Summary: Internationalized Resource Identifiers (IRIs)
Home-page: UNKNOWN
Author: Ivan D Vasin
Author-email: nisavid@gmail.com
License: GNU LESSER GENERAL PUBLIC LICENSE
Requires-Dist: goosetypes
